CONTRIBUTING.rst
HISTORY.rst
LICENSE
MANIFEST.in
README.rst
mpris_2.py
mpris_2_plus.py
setup.cfg
setup.py
kupfer_plugin_mpris_2.egg-info/PKG-INFO
kupfer_plugin_mpris_2.egg-info/SOURCES.txt
kupfer_plugin_mpris_2.egg-info/dependency_links.txt
kupfer_plugin_mpris_2.egg-info/not-zip-safe
kupfer_plugin_mpris_2.egg-info/requires.txt
kupfer_plugin_mpris_2.egg-info/top_level.txt