Metadata-Version: 1.1
Name: kupfer-plugin-mpris-2
Version: 0.1.0
Summary: Control any mpris2 media player
Home-page: https://github.com/hugosenari/mpris_2
Author: Hugo Sena Ribeiro
Author-email: hugosenari@gmail.com
License: MIT license
Keywords: kupfer mpris2
Platform: UNKNOWN
Classifier: Development Status :: 2 - Pre-Alpha
Classifier: Intended Audience :: Developers
Classifier: License :: OSI Approved :: MIT License
Classifier: Natural Language :: English
Classifier: Programming Language :: Python :: 2
Classifier: Programming Language :: Python :: 2.7
Classifier: Programming Language :: Python :: 3
Classifier: Programming Language :: Python :: 3.3
Classifier: Programming Language :: Python :: 3.4
Classifier: Programming Language :: Python :: 3.5
